dispatcher/__init__.py
dispatcher/dispatcher.py
dispatcher_enum-0.1.0.dist-info/LICENSE
dispatcher_enum-0.1.0.dist-info/METADATA
dispatcher_enum-0.1.0.dist-info/WHEEL
dispatcher_enum-0.1.0.dist-info/top_level.txt
dispatcher_enum-0.1.0.dist-info/RECORD
