Metadata-Version: 2.1
Name: dispatcher-enum
Version: 0.1.0
Summary: Config-file strategy pattern enabler: easily create Pydantic-friendly Enums with a function to call for each member
Home-page: https://github.com/asemic-horizon/dispatcher
Author: Diego Navarro
Author-email: the.electric.me@gmail.com
License: UNKNOWN
Platform: UNKNOWN
Classifier: Programming Language :: Python :: 3
Classifier: Operating System :: OS Independent
Requires-Python: >=3.6
License-File: LICENSE
